pytest_pycharm.py
pytest_pycharm-0.6.0.dist-info/AUTHORS.rst
pytest_pycharm-0.6.0.dist-info/LICENSE
pytest_pycharm-0.6.0.dist-info/METADATA
pytest_pycharm-0.6.0.dist-info/WHEEL
pytest_pycharm-0.6.0.dist-info/entry_points.txt
pytest_pycharm-0.6.0.dist-info/top_level.txt
pytest_pycharm-0.6.0.dist-info/RECORD
