Metadata-Version: 1.1
Name: pytest-pycharm
Version: 0.6.0
Summary: Plugin for py.test to enter PyCharm debugger on uncaught exceptions
Home-page: https://github.com/jlubcke/pytest-pycharm
Author: Johan Lübcke
Author-email: johan@lubcke.se
License: BSD
Keywords: pytest,py.test,pycharm
Platform: UNKNOWN
Classifier: Development Status :: 2 - Pre-Alpha
Classifier: Intended Audience :: Developers
Classifier: License :: OSI Approved :: BSD License
Classifier: Natural Language :: English
Classifier: Operating System :: POSIX
Classifier: Operating System :: Microsoft :: Windows
Classifier: Operating System :: MacOS :: MacOS X
Classifier: Topic :: Software Development :: Testing
Classifier: Topic :: Software Development :: Libraries
Classifier: Topic :: Utilities
Classifier: Programming Language :: Python :: 2
Classifier: Programming Language :: Python :: 2.6
Classifier: Programming Language :: Python :: 2.7
Classifier: Programming Language :: Python :: 3
Classifier: Programming Language :: Python :: 3.3
Classifier: Programming Language :: Python :: 3.4
